pycinc/__init__.py
pycinc/cic.py
pycinc/results.py
pycinc-0.2.0.dist-info/licenses/LICENSE
pycinc-0.2.0.dist-info/METADATA
pycinc-0.2.0.dist-info/WHEEL
pycinc-0.2.0.dist-info/top_level.txt
pycinc-0.2.0.dist-info/RECORD
